img2bw/__init__.py
img2bw/binarizer.py
img2bw/main.py
img2bw/utils.py
img2bw-0.2.1.dist-info/LICENSE
img2bw-0.2.1.dist-info/METADATA
img2bw-0.2.1.dist-info/WHEEL
img2bw-0.2.1.dist-info/entry_points.txt
img2bw-0.2.1.dist-info/top_level.txt
img2bw-0.2.1.dist-info/RECORD
