Metadata-Version: 2.1
Name: img2bw
Version: 0.2.1
Summary: Command-line application to binarize images
Home-page: https://github.com/salvacarrion/img2bw
Author: Salva Carrión
License: MIT
Platform: any
Requires-Dist: scikit-image (>=0.16.2)
Requires-Dist: pythreshold (>=0.2.1)
